zenfilter.py
Zenfilter-0.1a0.dist-info/DESCRIPTION.rst
Zenfilter-0.1a0.dist-info/METADATA
Zenfilter-0.1a0.dist-info/RECORD
Zenfilter-0.1a0.dist-info/WHEEL
Zenfilter-0.1a0.dist-info/entry_points.txt
Zenfilter-0.1a0.dist-info/metadata.json
Zenfilter-0.1a0.dist-info/top_level.txt
