Metadata-Version: 2.0
Name: Zenfilter
Version: 0.1a0
Summary: Filters TravisCI output
Home-page: UNKNOWN
Author: Trashlord
Author-email: dornenreich666@gmail.com
License: MIT
Keywords: travisci
Platform: UNKNOWN
Classifier: Development Status :: 3 - Alpha
Classifier: Programming Language :: Python :: 3
